__init__.py
linear_algebra.py
main.py
middleware.py
vector_calculus.py
visualization.py
mseep_numpy_mcp-0.1.1.dist-info/licenses/LICENSE
mseep_numpy_mcp-0.1.1.dist-info/METADATA
mseep_numpy_mcp-0.1.1.dist-info/WHEEL
mseep_numpy_mcp-0.1.1.dist-info/top_level.txt
mseep_numpy_mcp-0.1.1.dist-info/RECORD
